voltalis/__init__.py
voltalis/cli.py
voltalis/pandas.py
voltalis/types.py
voltalis/legacy/__init__.py
voltalis/legacy/cli.py
voltalis/legacy/voltalis_types.py
voltalis_cli-1.2.0.dist-info/LICENSE.txt
voltalis_cli-1.2.0.dist-info/METADATA
voltalis_cli-1.2.0.dist-info/WHEEL
voltalis_cli-1.2.0.dist-info/top_level.txt
voltalis_cli-1.2.0.dist-info/RECORD
