Metadata-Version: 2.1
Name: voltalis-cli
Version: 1.2.0
Summary: voltalis python client
Home-page: https://github.com/nilleb/voltalis-cli
Author: Ivo Bellin Salarin
Author-email: ivo@nilleb.com
License-File: LICENSE.txt
Requires-Dist: requests (>=1.11.1)
Provides-Extra: build
Requires-Dist: requests ; extra == 'build'
Requires-Dist: python-dateutilrequests-cache ; extra == 'build'
Requires-Dist: pandas ; extra == 'build'
Provides-Extra: dev
Requires-Dist: black ; extra == 'dev'
Requires-Dist: isort ; extra == 'dev'
Requires-Dist: ipython ; extra == 'dev'
Requires-Dist: build ; extra == 'dev'
Requires-Dist: twine ; extra == 'dev'
Requires-Dist: python-json-logger ; extra == 'dev'
